qtypi/__init__.py
qtypi/quantum_gates.py
qtypi/quantum_state.py
qtypi-0.1.0.dist-info/LICENSE
qtypi-0.1.0.dist-info/METADATA
qtypi-0.1.0.dist-info/WHEEL
qtypi-0.1.0.dist-info/top_level.txt
qtypi-0.1.0.dist-info/RECORD
