Metadata-Version: 2.1
Name: qtypi
Version: 0.1.0
Summary: A Python library for quantum state manipulations and quantum gates
Home-page: https://github.com/pearlpatel207/qtypi
Author: Pearl Patel
Author-email: pearl207@gmail.com
Classifier: Programming Language :: Python :: 3
Classifier: License :: OSI Approved :: MIT License
Classifier: Operating System :: OS Independent
Classifier: Topic :: Scientific/Engineering :: Physics
Classifier: Topic :: Software Development :: Libraries :: Python Modules
Requires-Python: >=3.6
License-File: LICENSE
Requires-Dist: numpy
